LICENSE
MANIFEST.in
README.md
setup.py
natural_language_terminal/.DS_Store
natural_language_terminal/__init__.py
natural_language_terminal/__main__.py
natural_language_terminal/create_env.py
natural_language_terminal/prompts.py
natural_language_terminal.egg-info/PKG-INFO
natural_language_terminal.egg-info/SOURCES.txt
natural_language_terminal.egg-info/dependency_links.txt
natural_language_terminal.egg-info/entry_points.txt
natural_language_terminal.egg-info/requires.txt
natural_language_terminal.egg-info/top_level.txt
natural_language_terminal/__pycache__/__init__.cpython-310.pyc
natural_language_terminal/__pycache__/create_env.cpython-310.pyc
natural_language_terminal/__pycache__/prompts.cpython-310.pyc
natural_language_terminal/cli/__init__.py
natural_language_terminal/cli/app.py
natural_language_terminal/cli/__pycache__/__init__.cpython-310.pyc
natural_language_terminal/cli/__pycache__/app.cpython-310.pyc
natural_language_terminal/core/system.py
natural_language_terminal/core/__pycache__/system.cpython-310.pyc
natural_language_terminal/git/autocommit.py
natural_language_terminal/git/__pycache__/autocommit.cpython-310.pyc
natural_language_terminal/shell_scripts/activate_template.bat
natural_language_terminal/shell_scripts/activate_template.sh
natural_language_terminal/shell_scripts/end_template.bat
natural_language_terminal/shell_scripts/end_template.sh
natural_language_terminal/shell_scripts/env_setter.sh
natural_language_terminal/shell_scripts/interceptor.sh
natural_language_terminal/terminal/base.py
natural_language_terminal/terminal/utils.py
natural_language_terminal/terminal/__pycache__/base.cpython-310.pyc
natural_language_terminal/terminal/__pycache__/utils.cpython-310.pyc