Metadata-Version: 2.1
Name: natural_language_terminal
Version: 0.1.9
Author: Balaji Rama
Author-email: balajirw10@gmail.com
Requires-Python: >=3.6
License-File: LICENSE
Requires-Dist: openai
Requires-Dist: typer
Requires-Dist: rich
Requires-Dist: python-dotenv
